match_detail.py
profile_detail.py
scrapeGG.py
utility.py
scrapeGG-0.0.5.dist-info/METADATA
scrapeGG-0.0.5.dist-info/WHEEL
scrapeGG-0.0.5.dist-info/top_level.txt
scrapeGG-0.0.5.dist-info/RECORD
