Metadata-Version: 2.1
Name: scrapeGG
Version: 0.0.5
Summary: Pulling League of Legends profile and match data from op.gg website.
Home-page: https://github.com/emily-yu/scrape.gg
Author: Emily Yu
Author-email: eyudeveloper@gmail.com
License: MIT
Keywords: league development selenium webscraper
Platform: UNKNOWN
Classifier: Programming Language :: Python :: 3
Classifier: License :: OSI Approved :: MIT License
Classifier: Operating System :: OS Independent
Requires-Python: >=3
